calculatorvadim.py
calculatorvadim-0.0.4.dist-info/LICENSE
calculatorvadim-0.0.4.dist-info/WHEEL
calculatorvadim-0.0.4.dist-info/METADATA
calculatorvadim-0.0.4.dist-info/RECORD
