Metadata-Version: 2.1
Name: calculatorvadim
Version: 0.0.4
Summary: This is my first experience creating a simple python calculator module.
Author-email: Vadim Iljin <vadim.iljin@gmail.com>
Classifier: License :: OSI Approved :: MIT License
Project-URL: Home, https://github.com/vadimiljin/calculatorvadim
